pyleo/__init__.py
pyleo/api.py
pyleo/constants.py
pyleo/utils.py
pyleo/abstractions/__init__.py
pyleo/abstractions/leoapi.py
pyleo/cli/__init__.py
pyleo/cli/command_line.py
pyleo/cli/utils.py
pyleo/exceptions/__init__.py
pyleo/exceptions/arg_error.py
pyleo-0.0.13.dist-info/LICENSE
pyleo-0.0.13.dist-info/METADATA
pyleo-0.0.13.dist-info/WHEEL
pyleo-0.0.13.dist-info/entry_points.txt
pyleo-0.0.13.dist-info/top_level.txt
pyleo-0.0.13.dist-info/RECORD
