Metadata-Version: 2.1
Name: pyleo
Version: 0.0.13
Summary: Unofficial Lingualeo API python library
Home-page: http://github.com/dorokhin/pyleo
Author: Andrew Dorokhin
Author-email: andrew@dorokhin.moscow
License: MIT
Keywords: pyleo api client lingualeo english-learning
Platform: UNKNOWN
Classifier: License :: OSI Approved :: MIT License
Classifier: Programming Language :: Python
Classifier: Programming Language :: Python :: 3.4
Classifier: Programming Language :: Python :: 3.5
Classifier: Programming Language :: Python :: 3.6
Classifier: Programming Language :: Python :: 3.7
Classifier: Natural Language :: English
Classifier: Operating System :: OS Independent
Classifier: Development Status :: 1 - Planning
Classifier: Intended Audience :: Developers
Classifier: Intended Audience :: Education
Classifier: Topic :: Software Development :: Libraries
Requires-Python: >=3.4
